evolvishub_ollama_adapter/__init__.py
evolvishub_ollama_adapter/client.py
evolvishub_ollama_adapter/config.py
evolvishub_ollama_adapter/constants.py
evolvishub_ollama_adapter/exceptions.py
evolvishub_ollama_adapter/file_utils.py
evolvishub_ollama_adapter/image_utils.py
evolvishub_ollama_adapter/logging.py
evolvishub_ollama_adapter/model_utils.py
evolvishub_ollama_adapter/text_utils.py
evolvishub_ollama_adapter/utils.py
evolvishub_ollama_adapter/assets/png/logo.png
evolvishub_ollama_adapter/databases/__init__.py
evolvishub_ollama_adapter/databases/base.py
evolvishub_ollama_adapter/databases/mongodb.py
evolvishub_ollama_adapter/databases/postgresql.py
evolvishub_ollama_adapter/databases/sqlite.py
evolvishub_ollama_adapter/ollama/__init__.py
evolvishub_ollama_adapter/ollama/models.py
evolvishub_ollama_adapter/ollama/utils.py
evolvishub_ollama_adapter/sources/__init__.py
evolvishub_ollama_adapter/sources/base.py
evolvishub_ollama_adapter/sources/binary.py
evolvishub_ollama_adapter/sources/file.py
evolvishub_ollama_adapter/sources/memory.py
evolvishub_ollama_adapter/sources/model.py
evolvishub_ollama_adapter/sources/ollama.py
evolvishub_ollama_adapter/sources/text.py
evolvishub_ollama_adapter-0.1.0.dist-info/licenses/LICENSE
evolvishub_ollama_adapter-0.1.0.dist-info/METADATA
evolvishub_ollama_adapter-0.1.0.dist-info/WHEEL
evolvishub_ollama_adapter-0.1.0.dist-info/top_level.txt
evolvishub_ollama_adapter-0.1.0.dist-info/RECORD
