Metadata-Version: 2.4
Name: evolvishub-ollama-adapter
Version: 0.1.0
Summary: A professional Python library for Ollama integration with support for multiple data sources
Home-page: https://github.com/evolvis/evolvishub-ollama-adapter
Author: Alban Maxhuni
Author-email: Evolvishub <info@evolvishub.com>
License: MIT
Project-URL: Documentation, https://evolvis.ai/docs/evolvishub-ollama-adapter
Project-URL: Source, https://github.com/evolvis/evolvishub-ollama-adapter
Project-URL: Tracker, https://github.com/evolvis/evolvishub-ollama-adapter/issues
Platform: unix
Platform: linux
Platform: osx
Platform: cygwin
Platform: win32
Classifier: Development Status :: 4 - Beta
Classifier: Intended Audience :: Developers
Classifier: Programming Language :: Python :: 3
Classifier: Programming Language :: Python :: 3.8
Classifier: Programming Language :: Python :: 3.9
Classifier: Programming Language :: Python :: 3.10
Classifier: Programming Language :: Python :: 3.11
Classifier: Programming Language :: Python :: 3.12
Requires-Python: >=3.8
License-File: LICENSE
Requires-Dist: requests>=2.31.0
Requires-Dist: pydantic>=2.0.0
Requires-Dist: python-dotenv>=1.0.0
Requires-Dist: aiohttp>=3.8.0
Requires-Dist: typing-extensions>=4.5.0
Provides-Extra: dev
Requires-Dist: pytest>=7.0.0; extra == "dev"
Requires-Dist: pytest-cov>=4.0.0; extra == "dev"
Requires-Dist: pytest-asyncio>=0.21.0; extra == "dev"
Requires-Dist: black>=23.0.0; extra == "dev"
Requires-Dist: isort>=5.12.0; extra == "dev"
Requires-Dist: mypy>=1.0.0; extra == "dev"
Requires-Dist: ruff>=0.1.0; extra == "dev"
Dynamic: author
Dynamic: home-page
Dynamic: license-file
Dynamic: requires-python
